gitwalk/__init__.py
gitwalk/walker.py
gitwalk-0.1.0.dist-info/METADATA
gitwalk-0.1.0.dist-info/WHEEL
gitwalk-0.1.0.dist-info/RECORD
